{"chromedocs_api reference - chrome developers.md":"2dee4e13","chromedocs_best practices_accessibility (a11y) - chrome developers.md":"b82404ea","chromedocs_best practices_declare permissions and warn users - chrome developers.md":"cad32cb8","chromedocs_best practices_give users options - chrome developers.md":"db797e06","chromedocs_best practices_localization message formats - chrome developers.md":"47edd00d","chromedocs_best practices_protect user privacy - chrome developers.md":"2dfb1735","chromedocs_best practices_stay secure - chrome developers.md":"83e48aca","chromedocs_develop extensions and themes_architecture overview - chrome developers.md":"5facaea8","chromedocs_develop extensions and themes_chrome extensions tutorial_ debugging extensions - chrome developers.md":"d525a823","chromedocs_develop extensions and themes_declare permissions - chrome developers.md":"74ade5e2","chromedocs_develop extensions and themes_design the user interface - chrome developers.md":"440d1f3b","chromedocs_develop extensions and themes_extension development overview - chrome developers.md":"1b923503","chromedocs_develop extensions and themes_manifest file format - chrome developers.md":"2959f19e","chromedocs_getting started guides_development basics - chrome developers.md":"fc3756f4","chromedocs_getting started guides_extensions 101 - chrome developers.md":"5f3df2ca","chromedocs_getting started guides_focus mode - chrome developers.md":"2f41e36e","chromedocs_getting started guides_reading time - chrome developers.md":"53ffb487","chromedocs_getting started guides_tabs manager - chrome developers.md":"a496ed4f","chromedocs_getting started guides_welcome - chrome developers.md":"564469a8","chromedocs_in depth_ core concepts_content scripts - chrome developers.md":"42696832","chromedocs_in depth_ core concepts_cross-origin isolation - chrome developers.md":"9ce41ca2","chromedocs_in depth_ core concepts_manage events with service workers - chrome developers.md":"72552eb6","chromedocs_in depth_ core concepts_match patterns - chrome developers.md":"c69bd0fe","chromedocs_in depth_ core concepts_message passing - chrome developers.md":"177f9f0c","chromedocs_in depth_ core concepts_using promises - chrome developers.md":"eee3e214","chromedocs_in depth_ more topics_chrome extensions tutorial_ oauth2 - authenticate users with google - chrome developers.md":"64b176b4","chromedocs_in depth_ more topics_extending devtools - chrome developers.md":"5e6192dd","chromedocs_in depth_ more topics_overriding chrome pages - chrome developers.md":"6b9616f6","chromedocs_in depth_ more topics_overriding chrome settings - chrome developers.md":"1863dde4","chromedocs_in depth_ more topics_rich notifications api - chrome developers.md":"9615903a","chromedocs_in depth_ security_cross-origin xmlhttprequest - chrome developers.md":"af3bac06","chromedocs_in depth_ security_using eval in chrome extensions - chrome developers.md":"37b9c72d","chromedocs_manifest v3_extensions platform vision - chrome developers.md":"4b303f45","chromedocs_manifest v3_overview of manifest v3 - chrome developers.md":"d1bf67fb","chromedocs_manifest v3_welcome to manifest v3 - chrome developers.md":"65731ba3","chromedocs_migrate from manifest v2 to manifest v3_known issues when migrating to manifest v3 - chrome developers.md":"4942969b","chromedocs_migrate from manifest v2 to manifest v3_manifest v2 support timeline - chrome developers.md":"54afff38","chromedocs_migrate from manifest v2 to manifest v3_manifest v3 migration checklist - chrome developers.md":"60f2814e","chromedocs_migrate from manifest v2 to manifest v3_migrating from background pages to service workers - chrome developers.md":"ca5a977e","chromedocs_migrate from manifest v2 to manifest v3_migrating to manifest v3 - chrome developers.md":"ea7fb060","chromedocs_overview_extensions quality guidelines faq - chrome developers.md":"beaa7590","chromedocs_overview_frequently asked questions - chrome developers.md":"93c0e4ea","chromedocs_overview_what are extensions_ - chrome developers.md":"b002f059","chromedocs_overview_what are themes_ - chrome developers.md":"42c0fd92","chromedocs_samples - chrome developers.md":"b5246b90","chromedocs_welcome - chrome developers.md":"11d4e078","chromedocs_whats new in chrome extensions - chrome developers.md":"90c0b248","chromedocs_distributing you extensions_alternative chrome extension installation methods - chrome developers.md":"36f7a2d8","chromedocs_distributing you extensions_extension hosting - chrome developers.md":"3891717b","chromedocs_distributing you extensions_installing extensions on linux - chrome developers.md":"bc70810d","chromedocs_distributing you extensions_tutorial_ google analytics - chrome developers.md":"453aa6ed","chromedocs_index.md":"803c254e","chromedocs_notebook_index.md":"059ea5b3","chromedocs_welcome.md":"54ac543e","components_components1.md":"0ef34510","components_index.md":"cff7a781","demo_index.md":"b3a73a00","guide_index.md":"215e6bdf","guide_installation.md":"1d0d9fd4","guide_quickstart.md":"85414567","index.md":"fa40652c","snippet_index.md":"6d1a226f","tools_community.md":"6af922b6","tools_demo.md":"3efb7cb8","tools_index.md":"28bb692d","tools_resources.md":"5cc6b5e0","tools_tools.md":"33defef8","tools_toy.md":"332f08c6","vitepressuse.md":"fe552b5e"}
